{
  "name": "Footers",
  "parent_id": null,
  "group_id": "61ce8b25-95ea-4399-bfd0-337a260306e3",
  "alternates": [],
  "created_at": "2024-10-09T15:48:32.465Z",
  "deleted_at": null,
  "sort_by_date": null,
  "tag_list": [],
  "updated_at": "2024-10-21T12:06:55.776Z",
  "published_at": "2024-10-21T12:06:55.750Z",
  "id": 560836300,
  "uuid": "324075a4-d232-4d85-84d2-fc7633eaaa7e",
  "is_folder": true,
  "content": {
    "content_types": [
      "footer"
    ],
    "lock_subfolders_content_types": true
  },
  "published": true,
  "slug": "footers",
  "path": null,
  "full_slug": "footers",
  "default_root": "footer",
  "disble_fe_editor": false,
  "disable_fe_editor": false,
  "parent": null,
  "is_startpage": false,
  "unpublished_changes": false,
  "meta_data": null,
  "imported_at": null,
  "pinned": false,
  "breadcrumbs": [],
  "publish_at": null,
  "expire_at": null,
  "first_published_at": "2024-10-21T12:06:55.750Z",
  "last_author": {
    "id": 178697,
    "userid": "dogfrogfog",
    "friendly_name": "maksim Hodasevich"
  },
  "last_author_id": 178697,
  "user_ids": [],
  "space_role_ids": [],
  "translated_slugs": [],
  "localized_paths": [],
  "position": -40,
  "translated_stories": [],
  "can_not_view": false,
  "is_scheduled": null,
  "scheduled_dates": null,
  "ideas": [],
  "stage": null,
  "favourite_for_user_ids": []
}